{"bookId":"beowulf","chapterIndex":43,"title":"XLII: Wiglaf’s Sad Story—The Hoard Carried Off","wordCount":625,"estimatedMinutes":3,"html":"\n\t\t<section id=\"chapter-42\" data-beowulf-fitt=\"42\" data-beowulf-fitt-line-count=\"75\">\n\t\t\t<hgroup>\n\t\t\t\t<h2>XLII</h2>\n\t\t\t\t<p>Wiglaf’s Sad Story⁠—The Hoard Carried Off</p>\n\t\t\t</hgroup>\n\t\t\t<p>\n\t\t\t\t<span data-beowulf-fitt=\"42\" data-beowulf-line=\"1\" data-beowulf-poem-line=\"2951\">Then ’twas seen that the journey prospered him little</span>\n\t\t\t\t<br>\n\t\t\t\t<span data-beowulf-fitt=\"42\" data-beowulf-line=\"2\" data-beowulf-poem-line=\"2952\">Who wrongly within had the ornaments hidden</span>\n\t\t\t\t<br>\n\t\t\t\t<span data-beowulf-fitt=\"42\" data-beowulf-line=\"3\" data-beowulf-poem-line=\"2953\">Down ’neath the wall. The warden erst slaughtered</span>\n\t\t\t\t<br>\n\t\t\t\t<span data-beowulf-fitt=\"42\" data-beowulf-line=\"4\" data-beowulf-poem-line=\"2954\">Some few of the folk-troop: the feud then thereafter</span>\n\t\t\t\t<br>\n\t\t\t\t<span data-beowulf-fitt=\"42\" data-beowulf-line=\"5\" data-beowulf-poem-line=\"2955\" data-beowulf-line-mark=\"5\">Was hotly avengèd. ’Tis a wonder where,</span>\n\t\t\t\t<br>\n\t\t\t\t<span data-beowulf-fitt=\"42\" data-beowulf-line=\"6\" data-beowulf-poem-line=\"2956\">When the strength-famous trooper has attained to the end of</span>\n\t\t\t\t<br>\n\t\t\t\t<span data-beowulf-fitt=\"42\" data-beowulf-line=\"7\" data-beowulf-poem-line=\"2957\">Life-days allotted, then no longer the man may</span>\n\t\t\t\t<br>\n\t\t\t\t<span data-beowulf-fitt=\"42\" data-beowulf-line=\"8\" data-beowulf-poem-line=\"2958\">Remain with his kinsmen where mead-cups are flowing.</span>\n\t\t\t\t<br>\n\t\t\t\t<span data-beowulf-fitt=\"42\" data-beowulf-line=\"9\" data-beowulf-poem-line=\"2959\">So to Beowulf happened when the ward of the barrow,</span>\n\t\t\t\t<br>\n\t\t\t\t<span data-beowulf-fitt=\"42\" data-beowulf-line=\"10\" data-beowulf-poem-line=\"2960\" data-beowulf-line-mark=\"10\">Assaults, he sought for: himself had no knowledge</span>\n\t\t\t\t<br>\n\t\t\t\t<span data-beowulf-fitt=\"42\" data-beowulf-line=\"11\" data-beowulf-poem-line=\"2961\">How his leaving this life was likely to happen.</span>\n\t\t\t\t<br>\n\t\t\t\t<span data-beowulf-fitt=\"42\" data-beowulf-line=\"12\" data-beowulf-poem-line=\"2962\">So to doomsday, famous folk-leaders down did</span>\n\t\t\t\t<br>\n\t\t\t\t<span data-beowulf-fitt=\"42\" data-beowulf-line=\"13\" data-beowulf-poem-line=\"2963\">Call it with curses⁠—who ’complished it there⁠—</span>\n\t\t\t\t<br>\n\t\t\t\t<span data-beowulf-fitt=\"42\" data-beowulf-line=\"14\" data-beowulf-poem-line=\"2964\">That that man should be ever of ill-deeds convicted,</span>\n\t\t\t\t<br>\n\t\t\t\t<span data-beowulf-fitt=\"42\" data-beowulf-line=\"15\" data-beowulf-poem-line=\"2965\" data-beowulf-line-mark=\"15\">Confined in foul-places, fastened in hell-bonds,</span>\n\t\t\t\t<br>\n\t\t\t\t<span data-beowulf-fitt=\"42\" data-beowulf-line=\"16\" data-beowulf-poem-line=\"2966\">Punished with plagues, who this place should e’er ravage.</span>\n\t\t\t\t<br>\n\t\t\t\t<span data-beowulf-fitt=\"42\" data-beowulf-line=\"17\" data-beowulf-poem-line=\"2967\">He cared not for gold: rather the Wielder’s</span>\n\t\t\t\t<br>\n\t\t\t\t<span data-beowulf-fitt=\"42\" data-beowulf-line=\"18\" data-beowulf-poem-line=\"2968\">Favor preferred he first to get sight of.</span>\n\t\t\t\t<br>\n\t\t\t\t<span data-beowulf-fitt=\"42\" data-beowulf-line=\"19\" data-beowulf-poem-line=\"2969\">Wiglaf discoursed then, Wihstan his son:</span>\n\t\t\t\t<br>\n\t\t\t\t<span data-beowulf-fitt=\"42\" data-beowulf-line=\"20\" data-beowulf-poem-line=\"2970\" data-beowulf-line-mark=\"20\">“Oft many an earlman on one man’s account must</span>\n\t\t\t\t<br>\n\t\t\t\t<span data-beowulf-fitt=\"42\" data-beowulf-line=\"21\" data-beowulf-poem-line=\"2971\">Sorrow endure, as to us it hath happened.</span>\n\t\t\t\t<br>\n\t\t\t\t<span data-beowulf-fitt=\"42\" data-beowulf-line=\"22\" data-beowulf-poem-line=\"2972\">The liegelord belovèd we could little prevail on,</span>\n\t\t\t\t<br>\n\t\t\t\t<span data-beowulf-fitt=\"42\" data-beowulf-line=\"23\" data-beowulf-poem-line=\"2973\">Kingdom’s keeper, counsel to follow,</span>\n\t\t\t\t<br>\n\t\t\t\t<span data-beowulf-fitt=\"42\" data-beowulf-line=\"24\" data-beowulf-poem-line=\"2974\">Not to go to the guardian of the gold-hoard, but let him</span>\n\t\t\t\t<br>\n\t\t\t\t<span data-beowulf-fitt=\"42\" data-beowulf-line=\"25\" data-beowulf-poem-line=\"2975\" data-beowulf-line-mark=\"25\">Lie where he long was, live in his dwelling</span>\n\t\t\t\t<br>\n\t\t\t\t<span data-beowulf-fitt=\"42\" data-beowulf-line=\"26\" data-beowulf-poem-line=\"2976\">Till the end of the world. Met we a destiny</span>\n\t\t\t\t<br>\n\t\t\t\t<span data-beowulf-fitt=\"42\" data-beowulf-line=\"27\" data-beowulf-poem-line=\"2977\">Hard to endure: the hoard has been looked at,</span>\n\t\t\t\t<br>\n\t\t\t\t<span data-beowulf-fitt=\"42\" data-beowulf-line=\"28\" data-beowulf-poem-line=\"2978\">Been gained very grimly; too grievous the fate that</span>\n\t\t\t\t<br>\n\t\t\t\t<span data-beowulf-fitt=\"42\" data-beowulf-line=\"29\" data-beowulf-poem-line=\"2979\">The prince of the people pricked to come thither.</span>\n\t\t\t\t<br>\n\t\t\t\t<span data-beowulf-fitt=\"42\" data-beowulf-line=\"30\" data-beowulf-poem-line=\"2980\" data-beowulf-line-mark=\"30\"><em>I</em> was therein and all of it looked at,</span>\n\t\t\t\t<br>\n\t\t\t\t<span data-beowulf-fitt=\"42\" data-beowulf-line=\"31\" data-beowulf-poem-line=\"2981\">The building’s equipments, since access was given me,</span>\n\t\t\t\t<br>\n\t\t\t\t<span data-beowulf-fitt=\"42\" data-beowulf-line=\"32\" data-beowulf-poem-line=\"2982\">Not kindly at all entrance permitted</span>\n\t\t\t\t<br>\n\t\t\t\t<span data-beowulf-fitt=\"42\" data-beowulf-line=\"33\" data-beowulf-poem-line=\"2983\">Within under earth-wall. Hastily seized I</span>\n\t\t\t\t<br>\n\t\t\t\t<span data-beowulf-fitt=\"42\" data-beowulf-line=\"34\" data-beowulf-poem-line=\"2984\">And held in my hands a huge-weighing burden</span>\n\t\t\t\t<br>\n\t\t\t\t<span data-beowulf-fitt=\"42\" data-beowulf-line=\"35\" data-beowulf-poem-line=\"2985\" data-beowulf-line-mark=\"35\">Of hoard-treasures costly, hither out bare them</span>\n\t\t\t\t<br>\n\t\t\t\t<span data-beowulf-fitt=\"42\" data-beowulf-line=\"36\" data-beowulf-poem-line=\"2986\">To my liegelord belovèd: life was yet in him,</span>\n\t\t\t\t<br>\n\t\t\t\t<span data-beowulf-fitt=\"42\" data-beowulf-line=\"37\" data-beowulf-poem-line=\"2987\">And consciousness also; the old one discoursed then</span>\n\t\t\t\t<br>\n\t\t\t\t<span data-beowulf-fitt=\"42\" data-beowulf-line=\"38\" data-beowulf-poem-line=\"2988\">Much and mournfully, commanded to greet you,</span>\n\t\t\t\t<br>\n\t\t\t\t<span data-beowulf-fitt=\"42\" data-beowulf-line=\"39\" data-beowulf-poem-line=\"2989\">Bade that remembering the deeds of your friend-lord</span>\n\t\t\t\t<br>\n\t\t\t\t<span data-beowulf-fitt=\"42\" data-beowulf-line=\"40\" data-beowulf-poem-line=\"2990\" data-beowulf-line-mark=\"40\">Ye build on the fire-hill of corpses a lofty</span>\n\t\t\t\t<br>\n\t\t\t\t<span data-beowulf-fitt=\"42\" data-beowulf-line=\"41\" data-beowulf-poem-line=\"2991\">Burial-barrow, broad and far-famous,</span>\n\t\t\t\t<br>\n\t\t\t\t<span data-beowulf-fitt=\"42\" data-beowulf-line=\"42\" data-beowulf-poem-line=\"2992\">As ’mid world-dwelling warriors he was widely most honored</span>\n\t\t\t\t<br>\n\t\t\t\t<span data-beowulf-fitt=\"42\" data-beowulf-line=\"43\" data-beowulf-poem-line=\"2993\">While he reveled in riches. Let us rouse us and hasten</span>\n\t\t\t\t<br>\n\t\t\t\t<span data-beowulf-fitt=\"42\" data-beowulf-line=\"44\" data-beowulf-poem-line=\"2994\">Again to see and seek for the treasure,</span>\n\t\t\t\t<br>\n\t\t\t\t<span data-beowulf-fitt=\"42\" data-beowulf-line=\"45\" data-beowulf-poem-line=\"2995\" data-beowulf-line-mark=\"45\">The wonder ’neath wall. The way I will show you,</span>\n\t\t\t\t<br>\n\t\t\t\t<span data-beowulf-fitt=\"42\" data-beowulf-line=\"46\" data-beowulf-poem-line=\"2996\">That close ye may look at ring-gems sufficient</span>\n\t\t\t\t<br>\n\t\t\t\t<span data-beowulf-fitt=\"42\" data-beowulf-line=\"47\" data-beowulf-poem-line=\"2997\">And gold in abundance. Let the bier with promptness</span>\n\t\t\t\t<br>\n\t\t\t\t<span data-beowulf-fitt=\"42\" data-beowulf-line=\"48\" data-beowulf-poem-line=\"2998\">Fully be fashioned, when forth we shall come,</span>\n\t\t\t\t<br>\n\t\t\t\t<span data-beowulf-fitt=\"42\" data-beowulf-line=\"49\" data-beowulf-poem-line=\"2999\">And lift we our lord, then, where long he shall tarry,</span>\n\t\t\t\t<br>\n\t\t\t\t<span data-beowulf-fitt=\"42\" data-beowulf-line=\"50\" data-beowulf-poem-line=\"3000\" data-beowulf-line-mark=\"50\">Well-beloved warrior, ’neath the Wielder’s protection.”</span>\n\t\t\t\t<br>\n\t\t\t\t<span data-beowulf-fitt=\"42\" data-beowulf-line=\"51\" data-beowulf-poem-line=\"3001\">Then the son of Wihstan bade orders be given,</span>\n\t\t\t\t<br>\n\t\t\t\t<span data-beowulf-fitt=\"42\" data-beowulf-line=\"52\" data-beowulf-poem-line=\"3002\">Mood-valiant man, to many of heroes,</span>\n\t\t\t\t<br>\n\t\t\t\t<span data-beowulf-fitt=\"42\" data-beowulf-line=\"53\" data-beowulf-poem-line=\"3003\">Holders of homesteads, that they hither from far,</span>\n\t\t\t\t<br>\n\t\t\t\t<span data-beowulf-fitt=\"42\" data-beowulf-line=\"54\" data-beowulf-poem-line=\"3004\">Leaders of liegemen, should look for the good one</span>\n\t\t\t\t<br>\n\t\t\t\t<span data-beowulf-fitt=\"42\" data-beowulf-line=\"55\" data-beowulf-poem-line=\"3005\" data-beowulf-line-mark=\"55\">With wood for his pyre: “The flame shall now swallow</span>\n\t\t\t\t<br>\n\t\t\t\t<span data-beowulf-fitt=\"42\" data-beowulf-line=\"56\" data-beowulf-poem-line=\"3006\">(The wan fire shall wax) the warriors’ leader</span>\n\t\t\t\t<br>\n\t\t\t\t<span data-beowulf-fitt=\"42\" data-beowulf-line=\"57\" data-beowulf-poem-line=\"3007\">Who the rain of the iron often abided,</span>\n\t\t\t\t<br>\n\t\t\t\t<span data-beowulf-fitt=\"42\" data-beowulf-line=\"58\" data-beowulf-poem-line=\"3008\">When, sturdily hurled, the storm of the arrows</span>\n\t\t\t\t<br>\n\t\t\t\t<span data-beowulf-fitt=\"42\" data-beowulf-line=\"59\" data-beowulf-poem-line=\"3009\">Leapt o’er linden-wall, the lance rendered service,</span>\n\t\t\t\t<br>\n\t\t\t\t<span data-beowulf-fitt=\"42\" data-beowulf-line=\"60\" data-beowulf-poem-line=\"3010\" data-beowulf-line-mark=\"60\">Furnished with feathers followed the arrow.”</span>\n\t\t\t\t<br>\n\t\t\t\t<span data-beowulf-fitt=\"42\" data-beowulf-line=\"61\" data-beowulf-poem-line=\"3011\">Now the wise-mooded son of Wihstan did summon</span>\n\t\t\t\t<br>\n\t\t\t\t<span data-beowulf-fitt=\"42\" data-beowulf-line=\"62\" data-beowulf-poem-line=\"3012\">The best of the braves from the band of the ruler</span>\n\t\t\t\t<br>\n\t\t\t\t<span data-beowulf-fitt=\"42\" data-beowulf-line=\"63\" data-beowulf-poem-line=\"3013\">Seven together; ’neath the enemy’s roof he</span>\n\t\t\t\t<br>\n\t\t\t\t<span data-beowulf-fitt=\"42\" data-beowulf-line=\"64\" data-beowulf-poem-line=\"3014\">Went with the seven; one of the heroes</span>\n\t\t\t\t<br>\n\t\t\t\t<span data-beowulf-fitt=\"42\" data-beowulf-line=\"65\" data-beowulf-poem-line=\"3015\" data-beowulf-line-mark=\"65\">Who fared at the front, a fire-blazing torch-light</span>\n\t\t\t\t<br>\n\t\t\t\t<span data-beowulf-fitt=\"42\" data-beowulf-line=\"66\" data-beowulf-poem-line=\"3016\">Bare in his hand. No lot then decided</span>\n\t\t\t\t<br>\n\t\t\t\t<span data-beowulf-fitt=\"42\" data-beowulf-line=\"67\" data-beowulf-poem-line=\"3017\">Who that hoard should havoc, when hero-earls saw it</span>\n\t\t\t\t<br>\n\t\t\t\t<span data-beowulf-fitt=\"42\" data-beowulf-line=\"68\" data-beowulf-poem-line=\"3018\">Lying in the cavern uncared-for entirely,</span>\n\t\t\t\t<br>\n\t\t\t\t<span data-beowulf-fitt=\"42\" data-beowulf-line=\"69\" data-beowulf-poem-line=\"3019\">Rusting to ruin: they rued then but little</span>\n\t\t\t\t<br>\n\t\t\t\t<span data-beowulf-fitt=\"42\" data-beowulf-line=\"70\" data-beowulf-poem-line=\"3020\" data-beowulf-line-mark=\"70\">That they hastily hence hauled out the treasure,</span>\n\t\t\t\t<br>\n\t\t\t\t<span data-beowulf-fitt=\"42\" data-beowulf-line=\"71\" data-beowulf-poem-line=\"3021\">The dear-valued jewels; the dragon eke pushed they,</span>\n\t\t\t\t<br>\n\t\t\t\t<span data-beowulf-fitt=\"42\" data-beowulf-line=\"72\" data-beowulf-poem-line=\"3022\">The worm o’er the wall, let the wave-currents take him,</span>\n\t\t\t\t<br>\n\t\t\t\t<span data-beowulf-fitt=\"42\" data-beowulf-line=\"73\" data-beowulf-poem-line=\"3023\">The waters enwind the ward of the treasures.</span>\n\t\t\t\t<br>\n\t\t\t\t<span data-beowulf-fitt=\"42\" data-beowulf-line=\"74\" data-beowulf-poem-line=\"3024\">There wounden gold on a wain was uploaded,</span>\n\t\t\t\t<br>\n\t\t\t\t<span data-beowulf-fitt=\"42\" data-beowulf-line=\"75\" data-beowulf-poem-line=\"3025\" data-beowulf-line-mark=\"75\">A mass unmeasured, the men-leader off then,</span>\n\t\t\t\t<br>\n\t\t\t\t<span>The hero hoary, to Whale’s-Ness was carried.</span>\n\t\t\t</p>\n\t\t</section>\n\t\n\n","fittNumber":42,"lineCount":75}