{"bookId":"mcteague","chapterIndex":0,"title":"Chapter 1","wordCount":1394,"estimatedMinutes":6,"html":"<h1>Forward</h1> <p>Frank Norris’s <em>McTeague</em> (1899) stands as a monument to the fierce and often brutal realism of late nineteenth-century American fiction. In this bleak narrative of greed and moral decay, Norris crafts a world governed by the ruthless logic of fate, where human will is both a spark of fragile dignity and a pitiless engine of destruction. To read <em>McTeague</em> is to encounter the grim determinism of a universe indifferent to the dreams of its inhabitants—yet also to witness the enduring grandeur of the soul’s struggle to make meaning within that implacable order.</p> <p>Norris’s prose is both muscular and unflinching, a language of feral precision that strips away every comfort of sentimental illusion. He is not content to render the surfaces of his world; he plunges us into its dark interiors, exposing the raw nerves of passion and the brute logic of appetite. In McTeague, Norris creates a protagonist who is at once monstrous and pitiable—a man whose violence and tenderness are woven from the same tragic fabric. This novel is no mere naturalistic document; it is a meditation on the monstrous grandeur of human desire and the remorseless force of the instincts that shape our fate.</p> <h2>The Language of Brutality and Beauty</h2> <p>One of the most striking aspects of <em>McTeague</em> is its language: a prose that is at once relentlessly direct and hauntingly lyrical. Norris writes with the economy of a realist and the somber poetry of a fatalist. In his descriptions of San Francisco’s Polk Street or the dusty mining camps of the Sierras, he captures both the coarse textures of the material world and the spectral glow of the mind’s own longings.</p> <p>This duality—this oscillation between brute fact and mythic resonance—gives Norris’s prose its peculiar power. He is not interested in sentimentality or in the consolations of moral didacticism. Rather, he insists on the terrible beauty of the real: the quiet grandeur of the streetcar’s rattle, the glint of the gold tooth in the dentist’s parlor, the hush of the desert winds that close around McTeague in the novel’s final pages. In these images, Norris suggests that even in the world’s most brutal economies, there is a music of fate that binds every gesture, every breath.</p> <h2>McTeague: The Tragic Beast</h2> <p>At the center of this dark panorama stands McTeague himself: a figure of brute innocence and inchoate hunger, whose violence is both animal and tragic. He is not a villain in the conventional sense; rather, he is a man whose instincts outstrip his reason, whose brute force carries within it a kind of melancholy grandeur. In McTeague’s lumbering silence, in his sudden rages and bewildered tenderness, we glimpse the tragic mystery of the human animal: the soul’s longing for order undone by the flesh’s endless demands.</p> <p>Norris does not ask us to love McTeague, but he does demand that we see him. In this, he echoes the ancient tragic poets, whose protagonists are not heroes of virtue but figures of elemental passion and ruin. McTeague’s tragedy is that he is both more and less than human: a creature of the body’s appetites, yet haunted by the flicker of something nobler, something that might have been if the world were not so indifferent and the self not so frail.</p> <h2>Trina and the Fetish of Gold</h2> <p>If McTeague is the tragic beast of the novel, Trina is its quiet fury: a woman whose fierce greed and fragile sensuality become the crucible of the story’s moral drama. In Trina, Norris reveals the corrosive power of gold not merely as a symbol but as an elemental force—an alchemy of desire that transforms even the most tender affections into instruments of ruin.</p> <p>Trina’s hoarding of the lottery money is more than an act of greed; it is a desperate assertion of control in a world that grants her little agency. Her money becomes her fortress and her tomb, a fetish that feeds her pride even as it devours her soul. Norris’s portrayal of Trina is both savage and sympathetic: he sees in her the victim of a brutal social economy and the agent of her own destruction. In this, he affirms the tragic doubleness of human passion: the way in which our dreams of security become the engines of our undoing.</p> <h2>The Irony of Desire</h2> <p>Throughout <em>McTeague</em>, Norris weaves an irony that is both tender and merciless: the irony of desire in a world that has no place for the illusions of the heart. McTeague and Trina’s marriage is at once a fulfillment and a betrayal of their hopes—a union that promises sanctuary but delivers only the quiet violence of mutual entrapment. In their fumbling courtship and their savage quarrels, Norris exposes the tragic gap between the soul’s hunger for communion and the body’s ceaseless appetite for possession.</p> <p>This irony extends to the larger world of the novel, where every gesture of love or kindness is shadowed by the play of power and the brute logic of survival. Marcus’s friendship with McTeague, Old Grannis’s shy courtship of Miss Baker—these are not sentimental subplots but counterpoints in the novel’s tragic music, echoes of the larger drama of human desire and its discontents.</p> <h2>The Landscape of the City and the Desert</h2> <p>In <em>McTeague</em>, the city of San Francisco and the deserts of the Sierras are more than settings: they are living forces in the moral landscape of the novel. Polk Street, with its cheap lodging houses and garish storefronts, is a world of petty commerce and stifled dreams, a stage upon which the soul’s quiet tragedies are played out. Norris’s evocation of the street’s grim poetry—its dusty windows, its flickering gaslights—reminds us that the true theatre of the tragic is not the battlefield or the court of kings, but the hush of the everyday.</p> <p>In the novel’s final chapters, the desert becomes a stage for the soul’s final reckoning. Here, in the silence of the mountains and the hush of the desert winds, the tragic grandeur of McTeague’s fate is laid bare. The image of the gold tooth glinting in the sun, the slow circling of the buzzards above the lifeless rocks—these are symbols of the eternal drama of appetite and ruin, of the soul’s final surrender to the music of fate.</p> <h2>The Moral Imagination and the Irony of Power</h2> <p>Yet for all its bleak determinism, <em>McTeague</em> is not a novel of nihilism. In its quiet ironies and its fierce lyricism, it affirms the power of the moral imagination: the soul’s refusal to be reconciled to its own undoing, the quiet grandeur of the self’s final gesture of defiance. Norris does not offer the comfort of redemption or the promise of transcendence. Instead, he insists on the tragic dignity of the struggle itself: the way in which even the most brutal fates can become the occasion for a kind of moral music.</p> <p>In this, Norris’s vision is both modern and ancient: modern in its unflinching realism, ancient in its recognition that the soul’s highest grandeur lies not in conquest but in the quiet fidelity of the heart to its own secret light. McTeague’s final flight into the desert is not a triumph, but neither is it a mere act of animal desperation. It is a gesture of the tragic imagination, a final testament to the soul’s refusal to be cowed by the brute indifference of the world.</p> <h2>Conclusion: The Music of the Abyss</h2> <p><em>McTeague</em> endures because it speaks to the part of us that is always in rebellion, always at war with the bright illusions of comfort and the easy pieties of progress. In its savage beauty and its quiet ironies, it affirms the truth that the soul’s highest grandeur is not in the triumph of reason or the victory of virtue, but in the music of the abyss: the song of the self that dares to sing even in the hush of the desert winds.</p> <p>In the flicker of McTeague’s final dream, in the hush of the desert’s final silence, we glimpse the shape of the soul’s own bright wonder—a wonder that refuses every consolation, yet endures as a testament to the quiet sovereignty of the imagination. In this, Norris gives us not a moral fable or a social tract, but a work of tragic art: a testament to the grandeur of the spirit’s own bright hunger and the music of the world’s indifferent light.</p>"}